awscloudwatchlogger/__init__.py
awscloudwatchlogger/awslogger.py
awscloudwatchlogger-0.2.dist-info/LICENSE
awscloudwatchlogger-0.2.dist-info/METADATA
awscloudwatchlogger-0.2.dist-info/WHEEL
awscloudwatchlogger-0.2.dist-info/top_level.txt
awscloudwatchlogger-0.2.dist-info/RECORD
