Metadata-Version: 2.1
Name: awscloudwatchlogger
Version: 0.2
Summary: Logging into aws cloudwatch from python apps
Author: Babasaheb Pinjar
Author-email: babasahebpinjar@gmail.com
Keywords: python,logger,cloudwatch
Classifier: Development Status :: 1 - Planning
Classifier: Intended Audience :: Developers
Classifier: Programming Language :: Python :: 3
Classifier: Operating System :: Unix
Classifier: Operating System :: MacOS :: MacOS X
Classifier: Operating System :: Microsoft :: Windows
License-File: LICENSE
Requires-Dist: boto3
